pieterraform/__init__.py
pieterraform/argument_base.py
pieterraform/common_args.py
pieterraform/context.py
pieterraform/level1.py
pieterraform/option_base.py
pieterraform/positional_base.py
pieterraform/runit.py
pieterraform/runner_base.py
pieterraform/terraform.py
pieterraform/tf_state.py
pieterraform/tf_vars.py
pieterraform/version.py
pieterraform-0.0.1a15.dist-info/LICENSE
pieterraform-0.0.1a15.dist-info/METADATA
pieterraform-0.0.1a15.dist-info/WHEEL
pieterraform-0.0.1a15.dist-info/top_level.txt
pieterraform-0.0.1a15.dist-info/RECORD
